Metadata-Version: 2.1
Name: mindColabYolo5
Version: 0.4
Summary: Descripción Demo
Home-page: UNKNOWN
Author: MindColab
Author-email: ramsesgiralald@gmail.com
License: UNKNOWN
Platform: UNKNOWN
License-File: LICENSE.txt
